{"is_source_file": true, "format": "md", "description": ".md file: README.md", "external_files": [], "external_methods": [], "published": [], "classes": [], "methods": [], "calls": [], "search-terms": ["README.md", "md"], "state": 2, "file_id": 9, "knowledge_revision": 32, "git_revision": "c3802ab06497024bc42dabe4a12ee4fc212738bd", "revision_history": [{"19": "c3802ab06497024bc42dabe4a12ee4fc212738bd"}, {"32": "c3802ab06497024bc42dabe4a12ee4fc212738bd"}], "filename": "todo_list_frontend/README.md", "format-version": 4, "code-base-name": "https://github.com/kavia-common/task-management-system-181011-181020.git:kavia-main"}